{
  "types": {
    "aliases": "aliases",
    "cssclasses": "multitext",
    "tags": "tags",
    "excalidraw-plugin": "text",
    "excalidraw-export-transparent": "checkbox",
    "excalidraw-mask": "checkbox",
    "excalidraw-export-dark": "checkbox",
    "excalidraw-export-padding": "number",
    "excalidraw-export-pngscale": "number",
    "excalidraw-link-prefix": "text",
    "excalidraw-url-prefix": "text",
    "excalidraw-link-brackets": "checkbox",
    "excalidraw-onload-script": "text",
    "excalidraw-linkbutton-opacity": "number",
    "excalidraw-default-mode": "text",
    "excalidraw-font": "text",
    "excalidraw-font-color": "text",
    "excalidraw-border-color": "text",
    "excalidraw-css": "text",
    "excalidraw-autoexport": "text",
    "excalidraw-iframe-theme": "text",
    "excalidraw-export-embed-scene": "checkbox",
    "excalidraw-open-md": "checkbox",
    "excalidraw-embeddable-theme": "text",
    "up": "multitext",
    "down": "multitext",
    "prev": "multitext",
    "after": "multitext",
    "before": "multitext",
    "BC-tag-note-tag": "text",
    "BC-tag-note-field": "text",
    "BC-tag-note-exact": "checkbox",
    "BC-regex-note-regex": "text",
    "BC-regex-note-flags": "text",
    "BC-regex-note-field": "text",
    "BC-folder-note-field": "text",
    "BC-folder-note-recurse": "checkbox",
    "BC-list-note-field": "text",
    "BC-list-note-neighbour-field": "text",
    "BC-list-note-exclude-index": "checkbox",
    "BC-dendron-note-field": "text",
    "BC-johnny-decimal-note-field": "text",
    "BC-dataview-note-query": "text",
    "BC-dataview-note-field": "text",
    "BC-ignore-in-edges": "checkbox",
    "BC-ignore-out-edges": "checkbox",
    "updated": "datetime",
    "id": "number",
    "created": "datetime",
    "category": "number",
    "publish": "checkbox",
    "hydrate": "checkbox",
    "steps": "checkbox",
    "meditate": "checkbox",
    "exercise": "checkbox",
    "read": "checkbox",
    "anki": "checkbox",
    "journal": "multitext",
    "timestamp": "text",
    "finished": "datetime",
    "related": "multitext",
    "efforts": "multitext",
    "same": "multitext",
    "next": "multitext",
    "eol": "checkbox",
    "title": "text",
    "type": "multitext"
  }
}